libname/__init__.py
libname/name.py
presma-0.0.1.dist-info/METADATA
presma-0.0.1.dist-info/WHEEL
presma-0.0.1.dist-info/top_level.txt
presma-0.0.1.dist-info/RECORD
